{
  "base/base.css": "base/base-11ac61fc9c.css",
  "base/common.css": "base/common-0487831bb7.css",
  "base/font.css": "base/font-590b94dc62.css",
  "base/frame.css": "base/frame-1f89e5f030.css",
  "bookshelf.css": "bookshelf-0142c8a836.css",
  "detail.css": "detail-3e5d272a0e.css",
  "index.css": "index-9f9d678d66.css",
  "list.css": "list-430aa8639f.css",
  "photo/base64Trans.css": "photo/base64Trans-5c87a995d0.css",
  "read.css": "read-8b7a1bb5a3.css",
  "yunying/optj.css": "yunying/optj-503425902f.css"
}